emu_utilities/__init__.py
emu_utilities/adjoint_gradient.py
emu_utilities/attribution.py
emu_utilities/convolution.py
emu_utilities/emu_utilities.py
emu_utilities/forward_gradient.py
emu_utilities/resample.py
emu_utilities/sampling.py
emu_utilities/tracer.py
emu_utilities/grid_data/AngleCS.data
emu_utilities/grid_data/AngleSN.data
emu_utilities/grid_data/DRC.data
emu_utilities/grid_data/DRF.data
emu_utilities/grid_data/DXC.data
emu_utilities/grid_data/DXG.data
emu_utilities/grid_data/DYC.data
emu_utilities/grid_data/DYG.data
emu_utilities/grid_data/RAC.data
emu_utilities/grid_data/RAS.data
emu_utilities/grid_data/RAW.data
emu_utilities/grid_data/RAZ.data
emu_utilities/grid_data/RC.data
emu_utilities/grid_data/RF.data
emu_utilities/grid_data/XC.data
emu_utilities/grid_data/XG.data
emu_utilities/grid_data/YC.data
emu_utilities/grid_data/YG.data
emu_utilities/grid_data/__init__.py
emu_utilities/grid_data/hFacC.data
emu_utilities/grid_data/hFacS.data
emu_utilities/grid_data/hFacW.data
emu_utilities-0.1.0.dist-info/METADATA
emu_utilities-0.1.0.dist-info/WHEEL
emu_utilities-0.1.0.dist-info/licenses/LICENSE
emu_utilities-0.1.0.dist-info/RECORD
