Metadata-Version: 2.4
Name: emu-utilities
Version: 0.1.0
Summary: Utilities for working with the outputs of the ECCO Modeling Utilities software.
Project-URL: Homepage, https://github.com/andrew-s28/emu-utilities
Project-URL: Repository, https://github.com/andrew-s28/emu-utilities
Project-URL: Issues, https://github.com/andrew-s28/emu-utilities/issues
Author-email: Andrew Scherer <scherand@oregonstate.edu>
Maintainer-email: Andrew Scherer <scherand@oregonstate.edu>
License: MIT
License-File: LICENSE
Keywords: climate,ecco,oceanography
Classifier: Development Status :: 4 - Beta
Classifier: Intended Audience :: Science/Research
Classifier: License :: OSI Approved :: MIT License
Classifier: Programming Language :: Python :: 3
Classifier: Programming Language :: Python :: 3.9
Classifier: Programming Language :: Python :: 3.10
Classifier: Programming Language :: Python :: 3.11
Classifier: Programming Language :: Python :: 3.12
Requires-Python: >=3.9
Requires-Dist: numpy>=2.0.2
Requires-Dist: pyresample>=1.31.0
Requires-Dist: xarray[io]>=2024.7.0
Requires-Dist: xmitgcm>=0.5.2
